[{"name":"Tachiyomi: E-Hentai","pkg":"eu.kanade.tachiyomi.extension.all.ehentai","apk":"eu.kanade.tachiyomi.extension.all.ehentai-v1.4.27.jar","lang":"all","code":27,"version":"1.4.27","nsfw":1,"sources":[]},{"name":"Tachiyomi: 3Hentai","pkg":"eu.kanade.tachiyomi.extension.all.hentai3","apk":"eu.kanade.tachiyomi.extension.all.hentai3-v1.4.3.jar","lang":"all","code":3,"version":"1.4.3","nsfw":1,"sources":[]},{"name":"Tachiyomi: Hitomi","pkg":"eu.kanade.tachiyomi.extension.all.hitomi","apk":"eu.kanade.tachiyomi.extension.all.hitomi-v1.4.41.jar","lang":"all","code":41,"version":"1.4.41","nsfw":1,"sources":[]},{"name":"Tachiyomi: NHentai","pkg":"eu.kanade.tachiyomi.extension.all.nhentai","apk":"eu.kanade.tachiyomi.extension.all.nhentai-v1.4.55.jar","lang":"all","code":55,"version":"1.4.55","nsfw":1,"sources":[]},{"name":"Tachiyomi: Pururin","pkg":"eu.kanade.tachiyomi.extension.all.pururin","apk":"eu.kanade.tachiyomi.extension.all.pururin-v1.4.10.jar","lang":"all","code":10,"version":"1.4.10","nsfw":1,"sources":[]},{"name":"Tachiyomi: Vortex Scans","pkg":"eu.kanade.tachiyomi.extension.en.arvenscans","apk":"eu.kanade.tachiyomi.extension.en.arvenscans-v1.4.1.jar","lang":"en","code":41,"version":"1.4.41","nsfw":0,"sources":[]},{"name":"Tachiyomi: Hentai20","pkg":"eu.kanade.tachiyomi.extension.en.hentai20","apk":"eu.kanade.tachiyomi.extension.en.hentai20-v1.4.1.jar","lang":"en","code":9,"version":"1.4.9","nsfw":1,"sources":[]},{"name":"Tachiyomi: Hentai2Read","pkg":"eu.kanade.tachiyomi.extension.en.hentai2read","apk":"eu.kanade.tachiyomi.extension.en.hentai2read-v1.4.18.jar","lang":"en","code":18,"version":"1.4.18","nsfw":1,"sources":[]},{"name":"Tachiyomi: HentaiMode","pkg":"eu.kanade.tachiyomi.extension.es.hentaimode","apk":"eu.kanade.tachiyomi.extension.es.hentaimode-v1.4.4.jar","lang":"es","code":4,"version":"1.4.4","nsfw":1,"sources":[]},{"name":"Tachiyomi: Noromax","pkg":"eu.kanade.tachiyomi.extension.id.noromax","apk":"eu.kanade.tachiyomi.extension.id.noromax-v1.4.1.jar","lang":"id","code":5,"version":"1.4.5","nsfw":0,"sources":[]},{"name":"Tachiyomi: Riztranslation","pkg":"eu.kanade.tachiyomi.extension.id.riztranslation","apk":"eu.kanade.tachiyomi.extension.id.riztranslation-v1.4.2.jar","lang":"id","code":2,"version":"1.4.2","nsfw":0,"sources":[]},{"name":"Tachiyomi: Softkomik","pkg":"eu.kanade.tachiyomi.extension.id.softkomik","apk":"eu.kanade.tachiyomi.extension.id.softkomik-v1.4.9.jar","lang":"id","code":9,"version":"1.4.9","nsfw":0,"sources":[]},{"name":"Tachiyomi: DDT Team","pkg":"eu.kanade.tachiyomi.extension.it.ddtteam","apk":"eu.kanade.tachiyomi.extension.it.ddtteam-v1.4.1.jar","lang":"it","code":0,"version":"1.4.0","nsfw":0,"sources":[]},{"name":"Tachiyomi: Comic Boost","pkg":"eu.kanade.tachiyomi.extension.ja.comicboost","apk":"eu.kanade.tachiyomi.extension.ja.comicboost-v1.4.2.jar","lang":"ja","code":2,"version":"1.4.2","nsfw":0,"sources":[]},{"name":"Tachiyomi: Comic Nettai","pkg":"eu.kanade.tachiyomi.extension.ja.comicnettai","apk":"eu.kanade.tachiyomi.extension.ja.comicnettai-v1.4.2.jar","lang":"ja","code":2,"version":"1.4.2","nsfw":0,"sources":[]},{"name":"Tachiyomi: Docomo","pkg":"eu.kanade.tachiyomi.extension.ja.docomo","apk":"eu.kanade.tachiyomi.extension.ja.docomo-v1.4.2.jar","lang":"ja","code":2,"version":"1.4.2","nsfw":0,"sources":[]},{"name":"Tachiyomi: Pash Up!","pkg":"eu.kanade.tachiyomi.extension.ja.pashup","apk":"eu.kanade.tachiyomi.extension.ja.pashup-v1.4.2.jar","lang":"ja","code":2,"version":"1.4.2","nsfw":0,"sources":[]},{"name":"Tachiyomi: RawDEX","pkg":"eu.kanade.tachiyomi.extension.ko.rawdex","apk":"eu.kanade.tachiyomi.extension.ko.rawdex-v1.4.1.jar","lang":"ko","code":2,"version":"1.4.2","nsfw":1,"sources":[]},{"name":"Tachiyomi: MoeTruyen","pkg":"eu.kanade.tachiyomi.extension.vi.moetruyen","apk":"eu.kanade.tachiyomi.extension.vi.moetruyen-v1.4.2.jar","lang":"vi","code":2,"version":"1.4.2","nsfw":0,"sources":[]}]